[{"sub_category": "Outdoor furniture", "product_info": [{"name": "\u00c4PPLAR\u00d6", "desc": "stool, outdoor, foldable brown stained", "price": "149", "product url": "https://www.ikea.cn/cn/en/p/aepplaroe-stool-outdoor-foldable-brown-stained-00204926/", "product code": "00204926"}]}, {"sub_category": "Outdoor furniture", "product_info": [{"name": "ASKHOLMEN", "desc": "table for wall+1 fold chr, outdoor, grey-brown stained/Fr\u00f6s\u00f6n/Duvholmen beige", "price": "467", "product url": "https://www.ikea.cn/cn/en/p/askholmen-table-for-wall-1-fold-chr-outdoor-grey-brown-stained-froesoen-duvholmen-beige-s09268947/", "product code": "09268947"}]}, {"sub_category": "Outdoor furniture", "product_info": [{"name": "FEJAN", "desc": "table+2 folding chairs, outdoor, white/white", "price": "299", "product url": "https://www.ikea.cn/cn/en/p/fejan-table-2-folding-chairs-outdoor-white-white-s39434950/", "product code": "39434950"}]}, {"sub_category": "Outdoor furniture", "product_info": [{"name": "\u00c4PPLAR\u00d6", "desc": "table+2 benches, outdoor, brown stained", "price": "2,497", "product url": "https://www.ikea.cn/cn/en/p/aepplaroe-table-2-benches-outdoor-brown-stained-s99053928/", "product code": "99053928"}]}, {"sub_category": "Outdoor furniture", "product_info": [{"name": "T\u00c4RN\u00d6", "desc": "table, outdoor, black/light brown stained, 100x54 cm", "price": "349", "product url": "https://www.ikea.cn/cn/en/p/taernoe-table-outdoor-black-light-brown-stained-10471938/", "product code": "10471938"}]}, {"sub_category": "Outdoor furniture", "product_info": [{"name": "\u00c4PPLAR\u00d6", "desc": "reclining chair, outdoor, foldable brown stained", "price": "424", "product url": "https://www.ikea.cn/cn/en/p/aepplaroe-reclining-chair-outdoor-foldable-brown-stained-50208540/", "product code": "50208540"}]}, {"sub_category": "Outdoor furniture", "product_info": [{"name": "FEJAN", "desc": "table, outdoor, grey, 50x44 cm", "price": "99", "product url": "https://www.ikea.cn/cn/en/p/fejan-table-outdoor-grey-10531999/", "product code": "10531999"}]}, {"sub_category": "Outdoor furniture", "product_info": [{"name": "JUTHOLMEN", "desc": "easy chair, outdoor, dark grey/Kuddarna beige, 65x73x83 cm", "price": "597", "product url": "https://www.ikea.cn/cn/en/p/jutholmen-easy-chair-outdoor-dark-grey-kuddarna-beige-s89385155/", "product code": "89385155"}]}, {"sub_category": "Outdoor furniture", "product_info": [{"name": "SJ\u00c4LLAND", "desc": "bar table and 2 bar stools, outdoor, light brown/light grey", "price": "2,197", "product url": "https://www.ikea.cn/cn/en/p/sjaelland-bar-table-and-2-bar-stools-outdoor-light-brown-light-grey-s19267848/", "product code": "19267848"}]}, {"sub_category": "Outdoor furniture", "product_info": [{"name": "T\u00c4RN\u00d6", "desc": "table+4 chairs, outdoor, red/light brown stained", "price": "865", "product url": "https://www.ikea.cn/cn/en/p/taernoe-table-4-chairs-outdoor-red-light-brown-stained-s09393630/", "product code": "09393630"}]}, {"sub_category": "Outdoor furniture", "product_info": [{"name": "ASKHOLMEN", "desc": "table f wall+2 fold chairs, outdoor, grey-brown stained/Fr\u00f6s\u00f6n/Duvholmen dark grey", "price": "736", "product url": "https://www.ikea.cn/cn/en/p/askholmen-table-f-wall-2-fold-chairs-outdoor-grey-brown-stained-froesoen-duvholmen-dark-grey-s39262312/", "product code": "39262312"}]}, {"sub_category": "Outdoor furniture", "product_info": [{"name": "TORPAR\u00d6", "desc": "table for wall+1 fold chr, outdoor, white/beige, 50 cm", "price": "255", "product url": "https://www.ikea.cn/cn/en/p/torparoe-table-for-wall-1-fold-chr-outdoor-white-beige-s39413660/", "product code": "39413660"}]}, {"sub_category": "Outdoor furniture", "product_info": [{"name": "TORPAR\u00d6", "desc": "table, in/outdoor, white/foldable, 70x42 cm", "price": "199", "product url": "https://www.ikea.cn/cn/en/p/torparoe-table-in-outdoor-white-foldable-40420749/", "product code": "40420749"}]}, {"sub_category": "Outdoor furniture", "product_info": [{"name": "TORPAR\u00d6", "desc": "table+4 reclining chairs, outdoor, white/beige, 130 cm", "price": "2,195", "product url": "https://www.ikea.cn/cn/en/p/torparoe-table-4-reclining-chairs-outdoor-white-beige-s89413672/", "product code": "89413672"}]}, {"sub_category": "Outdoor furniture", "product_info": [{"name": "BRUSEN", "desc": "3-seat sofa, outdoor, red", "price": "1,799", "product url": "https://www.ikea.cn/cn/en/p/brusen-3-seat-sofa-outdoor-red-50436354/", "product code": "50436354"}]}, {"sub_category": "Outdoor furniture", "product_info": [{"name": "TORPAR\u00d6", "desc": "reclining chair, outdoor, white/beige", "price": "399", "product url": "https://www.ikea.cn/cn/en/p/torparoe-reclining-chair-outdoor-white-beige-40461344/", "product code": "40461344"}]}, {"sub_category": "Outdoor furniture", "product_info": [{"name": "INGMARS\u00d6", "desc": "2-seat sofa, in/outdoor, white green/beige, 118x69x69 cm", "price": "499", "product url": "https://www.ikea.cn/cn/en/p/ingmarsoe-2-seat-sofa-in-outdoor-white-green-beige-50463291/", "product code": "50463291"}]}, {"sub_category": "Outdoor furniture", "product_info": [{"name": "\u00c4PPLAR\u00d6", "desc": "drop-leaf table, outdoor, brown stained, 140/200/260x78 cm", "price": "1,499", "product url": "https://www.ikea.cn/cn/en/p/aepplaroe-drop-leaf-table-outdoor-brown-stained-20208532/", "product code": "20208532"}]}, {"sub_category": "Outdoor furniture", "product_info": [{"name": "ASKHOLMEN", "desc": "table+4 folding chairs, outdoor, grey-brown stained/Kuddarna beige", "price": "1,314", "product url": "https://www.ikea.cn/cn/en/p/askholmen-table-4-folding-chairs-outdoor-grey-brown-stained-kuddarna-beige-s09286183/", "product code": "09286183"}]}, {"sub_category": "Outdoor furniture", "product_info": [{"name": "MASTHOLMEN", "desc": "2-seat conversation set, outdoor, rattan", "price": "1,798", "product url": "https://www.ikea.cn/cn/en/p/mastholmen-2-seat-conversation-set-outdoor-rattan-s39217522/", "product code": "39217522"}]}, {"sub_category": "Outdoor furniture", "product_info": [{"name": "\u00c4PPLAR\u00d6", "desc": "sun lounger, brown stained/Fr\u00f6s\u00f6n/Duvholmen beige", "price": "1,198", "product url": "https://www.ikea.cn/cn/en/p/aepplaroe-sun-lounger-brown-stained-froesoen-duvholmen-beige-s19444021/", "product code": "19444021"}]}, {"sub_category": "Outdoor furniture", "product_info": [{"name": "GUBB\u00d6N", "desc": "rocking-chair, in/outdoor, white", "price": "599", "product url": "https://www.ikea.cn/cn/en/p/gubboen-rocking-chair-in-outdoor-white-80479262/", "product code": "80479262"}]}, {"sub_category": "Outdoor furniture", "product_info": [{"name": "BONDHOLMEN", "desc": "table, outdoor, grey, 108 cm", "price": "1,299", "product url": "https://www.ikea.cn/cn/en/p/bondholmen-table-outdoor-grey-40420612/", "product code": "40420612"}]}, {"sub_category": "Outdoor furniture", "product_info": [{"name": "TORPAR\u00d6", "desc": "balcony table, white, 50 cm", "price": "129", "product url": "https://www.ikea.cn/cn/en/p/torparoe-balcony-table-white-50461348/", "product code": "50461348"}]}, {"sub_category": "Outdoor furniture", "product_info": [{"name": "\u00c4PPLAR\u00d6", "desc": "bench with wall panel, outdoor, brown stained, 80x44x158 cm", "price": "798", "product url": "https://www.ikea.cn/cn/en/p/aepplaroe-bench-with-wall-panel-outdoor-brown-stained-s09898343/", "product code": "09898343"}]}]